ManageDB/__init__.py
managedb-0.1.dist-info/LICENSE.txt
managedb-0.1.dist-info/METADATA
managedb-0.1.dist-info/WHEEL
managedb-0.1.dist-info/top_level.txt
managedb-0.1.dist-info/RECORD
