Metadata-Version: 2.2
Name: ManageDB
Version: 0.1
Summary: A library dedicated to easy and seamless handling of sqlite3 / db files
Home-page: https://t.me/midoghanam
Author: Mohammed Ahmed Ghanam
Author-email: Mohamed Ahmed Ghanam <mghanam883@outlook.com>
License: MIT
Project-URL: Homepage, https://t.me/mido_ghanam
Project-URL: My_Telegram_Account, https://t.me/midoghanam
Project-URL: EgyptianProgrammers, https://t.me/egyptionprogrammers
Project-URL: Whatsapp, https://wa.me/201101023681
Requires-Python: >=3.6
License-File: LICENSE.txt
Dynamic: author
Dynamic: home-page
Dynamic: requires-python
